elm/__init__.py
elm/base.py
elm/chunk.py
elm/cli.py
elm/embed.py
elm/exceptions.py
elm/pdf.py
elm/summary.py
elm/tree.py
elm/version.py
elm/wizard.py
elm/ords/__init__.py
elm/ords/download.py
elm/ords/process.py
elm/ords/extraction/__init__.py
elm/ords/extraction/apply.py
elm/ords/extraction/date.py
elm/ords/extraction/features.py
elm/ords/extraction/graphs.py
elm/ords/extraction/ngrams.py
elm/ords/extraction/ordinance.py
elm/ords/extraction/parse.py
elm/ords/extraction/tree.py
elm/ords/llm/__init__.py
elm/ords/llm/calling.py
elm/ords/services/__init__.py
elm/ords/services/base.py
elm/ords/services/cpu.py
elm/ords/services/openai.py
elm/ords/services/provider.py
elm/ords/services/queues.py
elm/ords/services/threaded.py
elm/ords/services/usage.py
elm/ords/utilities/__init__.py
elm/ords/utilities/counties.py
elm/ords/utilities/exceptions.py
elm/ords/utilities/location.py
elm/ords/utilities/parsing.py
elm/ords/utilities/queued_logging.py
elm/ords/validation/__init__.py
elm/ords/validation/content.py
elm/ords/validation/location.py
elm/utilities/__init__.py
elm/utilities/parse.py
elm/utilities/retry.py
elm/utilities/try_import.py
elm/utilities/validation.py
elm/web/__init__.py
elm/web/document.py
elm/web/file_loader.py
elm/web/html_pw.py
elm/web/osti.py
elm/web/rhub.py
elm/web/utilities.py
elm/web/website_crawl.py
elm/web/search/__init__.py
elm/web/search/base.py
elm/web/search/bing.py
elm/web/search/duckduckgo.py
elm/web/search/dux.py
elm/web/search/google.py
elm/web/search/run.py
elm/web/search/tavily.py
elm/web/search/yahoo.py
NREL_elm-0.0.31.dist-info/LICENSE.txt
NREL_elm-0.0.31.dist-info/METADATA
NREL_elm-0.0.31.dist-info/WHEEL
NREL_elm-0.0.31.dist-info/entry_points.txt
NREL_elm-0.0.31.dist-info/top_level.txt
NREL_elm-0.0.31.dist-info/RECORD
