Metadata-Version: 2.1
Name: NREL-elm
Version: 0.0.31
Summary: Energy Language Model
Home-page: https://github.com/NREL/elm
Author: Grant Buster
Author-email: grant.buster@nrel.gov
License: BSD 3-Clause
Keywords: elm
Platform: UNKNOWN
Classifier: Development Status :: 4 - Beta
Classifier: Intended Audience :: Science/Research
Classifier: License :: OSI Approved :: BSD License
Classifier: Natural Language :: English
Classifier: Programming Language :: Python :: 3.9
Classifier: Programming Language :: Python :: 3.10
Classifier: Programming Language :: Python :: 3.11
Requires-Python: >=3.9
License-File: LICENSE.txt
Requires-Dist: openai>=1.1.0
Requires-Dist: aiohttp
Requires-Dist: beautifulsoup4
Requires-Dist: camoufox
Requires-Dist: click
Requires-Dist: crawl4ai
Requires-Dist: ddgs
Requires-Dist: fake-useragent>=2.0.3
Requires-Dist: google-api-python-client
Requires-Dist: google-search-results
Requires-Dist: html2text
Requires-Dist: httpx
Requires-Dist: langchain-text-splitters
Requires-Dist: lxml
Requires-Dist: matplotlib
Requires-Dist: networkx
Requires-Dist: nrel-rex
Requires-Dist: nltk
Requires-Dist: numpy
Requires-Dist: pandas
Requires-Dist: tf-playwright-stealth
Requires-Dist: PyPDF2
Requires-Dist: python-slugify
Requires-Dist: rebrowser-playwright
Requires-Dist: scipy
Requires-Dist: scrapling
Requires-Dist: tabulate
Requires-Dist: tavily-python
Requires-Dist: tiktoken
Provides-Extra: dev
Requires-Dist: openai>=1.1.0; extra == "dev"
Requires-Dist: aiohttp; extra == "dev"
Requires-Dist: beautifulsoup4; extra == "dev"
Requires-Dist: camoufox; extra == "dev"
Requires-Dist: click; extra == "dev"
Requires-Dist: crawl4ai; extra == "dev"
Requires-Dist: ddgs; extra == "dev"
Requires-Dist: fake-useragent>=2.0.3; extra == "dev"
Requires-Dist: google-api-python-client; extra == "dev"
Requires-Dist: google-search-results; extra == "dev"
Requires-Dist: html2text; extra == "dev"
Requires-Dist: httpx; extra == "dev"
Requires-Dist: langchain-text-splitters; extra == "dev"
Requires-Dist: lxml; extra == "dev"
Requires-Dist: matplotlib; extra == "dev"
Requires-Dist: networkx; extra == "dev"
Requires-Dist: nrel-rex; extra == "dev"
Requires-Dist: nltk; extra == "dev"
Requires-Dist: numpy; extra == "dev"
Requires-Dist: pandas; extra == "dev"
Requires-Dist: tf-playwright-stealth; extra == "dev"
Requires-Dist: PyPDF2; extra == "dev"
Requires-Dist: python-slugify; extra == "dev"
Requires-Dist: rebrowser-playwright; extra == "dev"
Requires-Dist: scipy; extra == "dev"
Requires-Dist: scrapling; extra == "dev"
Requires-Dist: tabulate; extra == "dev"
Requires-Dist: tavily-python; extra == "dev"
Requires-Dist: tiktoken; extra == "dev"
Requires-Dist: pytest>=5.2; extra == "dev"
Requires-Dist: pytest-mock; extra == "dev"
Requires-Dist: pytest-asyncio; extra == "dev"
Requires-Dist: pytest-cov; extra == "dev"
Requires-Dist: flaky>=3.8.1; extra == "dev"
